app/__init__.py
app/admin.py
app/apps.py
app/asgi.py
app/models.py
app/settings.py
app/urls.py
app/wsgi.py
app/fixtures/__init__.py
app/management/__init__.py
app/management/commands/__init__.py
app/management/commands/init.py
app/migrations/0001_initial.py
app/migrations/__init__.py
django_admin_tailwind/__init__.py
django_admin_tailwind/apps.py
django_admin_tailwind/context.py
django_admin_tailwind/dynamic_pagination.py
django_admin_tailwind/filters.py
django_admin_tailwind/preview_url.py
django_admin_tailwind/templates/admin/404.html
django_admin_tailwind/templates/admin/500.html
django_admin_tailwind/templates/admin/actions.html
django_admin_tailwind/templates/admin/app_index.html
django_admin_tailwind/templates/admin/app_list.html
django_admin_tailwind/templates/admin/base.html
django_admin_tailwind/templates/admin/base_site.html
django_admin_tailwind/templates/admin/change_form.html
django_admin_tailwind/templates/admin/change_form_object_tools.html
django_admin_tailwind/templates/admin/change_list.html
django_admin_tailwind/templates/admin/change_list_object_tools.html
django_admin_tailwind/templates/admin/change_list_results.html
django_admin_tailwind/templates/admin/date_hierarchy.html
django_admin_tailwind/templates/admin/delete_confirmation.html
django_admin_tailwind/templates/admin/delete_selected_confirmation.html
django_admin_tailwind/templates/admin/filter.html
django_admin_tailwind/templates/admin/index.html
django_admin_tailwind/templates/admin/invalid_setup.html
django_admin_tailwind/templates/admin/login.html
django_admin_tailwind/templates/admin/nav_sidebar.html
django_admin_tailwind/templates/admin/object_history.html
django_admin_tailwind/templates/admin/pagination.html
django_admin_tailwind/templates/admin/popup_response.html
django_admin_tailwind/templates/admin/prepopulated_fields_js.html
django_admin_tailwind/templates/admin/search_form.html
django_admin_tailwind/templates/admin/submit_line.html
django_admin_tailwind-0.0.29.dist-info/LICENSE
django_admin_tailwind-0.0.29.dist-info/METADATA
django_admin_tailwind-0.0.29.dist-info/WHEEL
django_admin_tailwind-0.0.29.dist-info/top_level.txt
django_admin_tailwind-0.0.29.dist-info/RECORD
