Metadata-Version: 2.1
Name: django-admin-tailwind
Version: 0.0.29
Summary: Django Admin Tailwind
Home-page: https://github.com/Aleksi44/django-admin-tailwind
Author: Alexis Le Baron
Author-email: hello@snoweb.fr
License: GPL-3.0
Keywords: django django-admin tailwind
Platform: linux
Classifier: Environment :: Web Environment
Classifier: Intended Audience :: Developers
Classifier: Programming Language :: Python
Classifier: Programming Language :: Python :: 3
Classifier: Programming Language :: Python :: 3.6
Classifier: Programming Language :: Python :: 3.7
Classifier: Programming Language :: Python :: 3.8
Classifier: Programming Language :: Python :: 3.9
Classifier: Operating System :: OS Independent
Classifier: Topic :: Software Development
License-File: LICENSE
